mp3_manager/__init__.py
mp3_manager/main.py
mp3_manager/mp3_manager.py
mp3_manager/terminal.py
mp3_manager-2.0.2.dist-info/LICENSE
mp3_manager-2.0.2.dist-info/METADATA
mp3_manager-2.0.2.dist-info/WHEEL
mp3_manager-2.0.2.dist-info/entry_points.txt
mp3_manager-2.0.2.dist-info/top_level.txt
mp3_manager-2.0.2.dist-info/RECORD
